{
  "lastUpdate": "19.02.2026 09:33:48",
  "date": "19 Şubat 2026",
  "marketSentiment": "BULLISH",
  "sentimentScore": 72,
  "summary": "Piyasa genel olarak nötr seyrediyor.",
  "topOpportunity": "BTC güçlü destek üzerinde.",
  "topRisk": "Küresel likidite belirsizliği.",
  "prices": {
    "btc": {
      "price": 67096,
      "change24h": -1.4990059179110486
    },
    "eth": {
      "price": 1976.99,
      "change24h": -2.0713952311909734
    },
    "sol": {
      "price": 81.84,
      "change24h": -4.360134187630478
    },
    "xrp": {
      "price": 1.42,
      "change24h": -4.147784455320829
    }
  },
  "trendingCoins": [
    "Optimism",
    "Pudgy Penguins",
    "Hyperliquid",
    "Espresso",
    "Ethereum"
  ],
  "signals": [
    {
      "id": 0,
      "expert": "Willy Woo",
      "asset": "BTC",
      "type": "BULL",
      "confidence": "High",
      "text": "On-chain metrikler güçlü",
      "time": "09:33"
    },
    {
      "id": 1,
      "expert": "Arthur Hayes",
      "asset": "ETH",
      "type": "BULL",
      "confidence": "Med",
      "text": "Likidite koşulları olumlu",
      "time": "09:33"
    },
    {
      "id": 2,
      "expert": "PlanB",
      "asset": "BTC",
      "type": "BULL",
      "confidence": "High",
      "text": "Model hedefi işaret ediyor",
      "time": "09:33"
    },
    {
      "id": 3,
      "expert": "Raoul Pal",
      "asset": "SOL",
      "type": "NEU",
      "confidence": "Low",
      "text": "Bekleme modunda",
      "time": "09:33"
    },
    {
      "id": 4,
      "expert": "Lyn Alden",
      "asset": "XRP",
      "type": "BULL",
      "confidence": "Med",
      "text": "Makro uyumlu",
      "time": "09:33"
    }
  ]
}